FoxDot/__init__.py
FoxDot/__main__.py
FoxDot/demo/00_intro.py
FoxDot/demo/01_playing_notes.py
FoxDot/demo/02_algorithmic_manipulation.py
FoxDot/demo/03_playing_samples.py
FoxDot/demo/04_using_patterns.py
FoxDot/demo/05_player_attributes.py
FoxDot/demo/06_rests.py
FoxDot/demo/07_basic_clock.py
FoxDot/demo/08_scales.py
FoxDot/demo/09_groups.py
FoxDot/demo/11_using_vars.py
FoxDot/demo/12_playing_custom_samples.py
FoxDot/demo/12_synthdefs.py
FoxDot/demo/13_advanced_clock.py
FoxDot/demo/14_player_attributes_reference.py
FoxDot/demo/15_pattern_generator_reference.py
FoxDot/lib/Bang.py
FoxDot/lib/Buffers.py
FoxDot/lib/Constants.py
FoxDot/lib/Effects.py
FoxDot/lib/Key.py
FoxDot/lib/Logging.py
FoxDot/lib/Midi.py
FoxDot/lib/OSC.py
FoxDot/lib/OSC3.py
FoxDot/lib/Players.py
FoxDot/lib/Repeat.py
FoxDot/lib/Root.py
FoxDot/lib/Scale.py
FoxDot/lib/ServerManager.py
FoxDot/lib/TempoClock.py
FoxDot/lib/TimeVar.py
FoxDot/lib/__init__.py
FoxDot/lib/Code/__init__.py
FoxDot/lib/Code/foxdot_func_cmp.py
FoxDot/lib/Code/foxdot_live_function.py
FoxDot/lib/Code/foxdot_tokenize.py
FoxDot/lib/Code/foxdot_when_statement.py
FoxDot/lib/Code/main_lib.py
FoxDot/lib/Custom/Fractal.py
FoxDot/lib/Custom/__init__.py
FoxDot/lib/Custom/webcam.py
FoxDot/lib/Extensions/SonicPi.py
FoxDot/lib/Extensions/__init__.py
FoxDot/lib/Extensions/generate_sonic_pi.py
FoxDot/lib/Extensions/sonicpi.json
FoxDot/lib/Patterns/Generators.py
FoxDot/lib/Patterns/Main.py
FoxDot/lib/Patterns/Operations.py
FoxDot/lib/Patterns/PGroups.py
FoxDot/lib/Patterns/Parse.py
FoxDot/lib/Patterns/PlayString.py
FoxDot/lib/Patterns/Sequences.py
FoxDot/lib/Patterns/Utils.py
FoxDot/lib/Patterns/__init__.py
FoxDot/lib/SCLang/Env.py
FoxDot/lib/SCLang/SCLang.py
FoxDot/lib/SCLang/SynthDef.py
FoxDot/lib/SCLang/_SynthDefs.py
FoxDot/lib/SCLang/__init__.py
FoxDot/lib/Settings/__init__.py
FoxDot/lib/Settings/conf.py
FoxDot/lib/Settings/conf.txt
FoxDot/lib/Utils/__init__.py
FoxDot-0.6.4.dist-info/METADATA
FoxDot-0.6.4.dist-info/RECORD
FoxDot-0.6.4.dist-info/WHEEL
FoxDot-0.6.4.dist-info/entry_points.txt
FoxDot-0.6.4.dist-info/top_level.txt
