Metadata-Version: 2.1
Name: FoxDot
Version: 0.6.4
Summary: Live coding music with SuperCollider
Home-page: http://foxdot.org/
Author: Ryan Kirkbride
Author-email: ryan@foxdot.org
License: UNKNOWN
Platform: UNKNOWN
